gffanalyzer_m1bioinfo/__init__.py
gffanalyzer_m1bioinfo/__main__.py
gffanalyzer_m1bioinfo/annotation.py
gffanalyzer_m1bioinfo-0.2.2.dist-info/METADATA
gffanalyzer_m1bioinfo-0.2.2.dist-info/WHEEL
gffanalyzer_m1bioinfo-0.2.2.dist-info/RECORD
