Metadata-Version: 2.3
Name: gffanalyzer_m1bioinfo
Version: 0.2.2
Summary: Add your description here
Requires-Python: >=3.10
Requires-Dist: matplotlib>=3.9.2
